gign-1.0.2.dist-info/licenses/LICENSE
gitignore_gen/__init__.py
gitignore_gen/cli.py
gitignore_gen/core.py
gitignore_gen/detector.py
gitignore_gen/exceptions.py
gitignore_gen/utils.py
gign-1.0.2.dist-info/METADATA
gign-1.0.2.dist-info/WHEEL
gign-1.0.2.dist-info/entry_points.txt
gign-1.0.2.dist-info/top_level.txt
gign-1.0.2.dist-info/RECORD
