Metadata-Version: 2.4
Name: gign
Version: 1.0.2
Summary: A magical CLI tool that automatically generates and manages .gitignore files
Author-email: sherin joseph roy <sherin.joseph2217@gmail.com>
Maintainer-email: sherin joseph roy <sherin.joseph2217@gmail.com>
License: MIT
Project-URL: Homepage, https://github.com/Sherin-SEF-AI/gitignore-gen
Project-URL: Documentation, https://github.com/Sherin-SEF-AI/gitignore-gen#readme
Project-URL: Repository, https://github.com/Sherin-SEF-AI/gitignore-gen
Project-URL: Bug Tracker, https://github.com/Sherin-SEF-AI/gitignore-gen/issues
Project-URL: Changelog, https://github.com/Sherin-SEF-AI/gitignore-gen/blob/main/CHANGELOG.md
Keywords: git,gitignore,cli,developer-tools,automation
Classifier: Development Status :: 5 - Production/Stable
Classifier: Intended Audience :: Developers
Classifier: License :: OSI Approved :: MIT License
Classifier: Operating System :: OS Independent
Classifier: Programming Language :: Python :: 3
Classifier: Programming Language :: Python :: 3.8
Classifier: Programming Language :: Python :: 3.9
Classifier: Programming Language :: Python :: 3.10
Classifier: Programming Language :: Python :: 3.11
Classifier: Programming Language :: Python :: 3.12
Classifier: Topic :: Software Development :: Libraries :: Python Modules
Classifier: Topic :: Software Development :: Version Control :: Git
Requires-Python: >=3.8
License-File: LICENSE
Requires-Dist: click>=8.1.0
Requires-Dist: rich>=13.0.0
Requires-Dist: colorama>=0.4.6
Requires-Dist: requests>=2.31.0
Requires-Dist: gitpython>=3.1.0
Requires-Dist: pyyaml>=6.0
Requires-Dist: toml>=0.10.2
Requires-Dist: aiohttp>=3.8.0
Requires-Dist: aiofiles>=23.0.0
Requires-Dist: pathspec>=0.11.0
Requires-Dist: typing-extensions>=4.5.0
Requires-Dist: watchdog>=3.0.0
Provides-Extra: dev
Requires-Dist: pytest>=7.0.0; extra == "dev"
Requires-Dist: pytest-asyncio>=0.21.0; extra == "dev"
Requires-Dist: pytest-cov>=4.0.0; extra == "dev"
Requires-Dist: pytest-mock>=3.10.0; extra == "dev"
Requires-Dist: black>=23.0.0; extra == "dev"
Requires-Dist: isort>=5.12.0; extra == "dev"
Requires-Dist: flake8>=6.0.0; extra == "dev"
Requires-Dist: mypy>=1.0.0; extra == "dev"
Requires-Dist: pre-commit>=3.0.0; extra == "dev"
Requires-Dist: twine>=4.0.0; extra == "dev"
Requires-Dist: build>=0.10.0; extra == "dev"
Provides-Extra: watch
Requires-Dist: watchdog>=3.0.0; extra == "watch"
Dynamic: license-file
